Workbook
Name CriteriosConsultaProduto: 'Quadro de Resumo'!$AM$7:$AM$8
Name Lista_Produtos: TB_Produtos[[#All],[Produto]]
Name Lista_Produtos: TB_Produtos[[#All],[Produto]]

Sheet Produtos
E1: Cadastro de Produtos
B4: Produto | C4: Unidade de Medida | D4: Estoque Mínimo | E4: Custo Unitário | F4: Preço Unitário
B5: Café | C5: Unidade | D5: 50 | E5: 2 | F5: 6
B6: Pão | C6: Kg | D6: 5 | E6: 1.5 | F6: 3
B7: Coxinha | C7: Kg | D7: 50 | E7: 0.5 | F7: 6.5
B8: Esfiha | C8: Kg | D8: 50 | E8: 1 | F8: 4.5
B9: Risoles | C9: Kg | D9: 50 | E9: 1 | F9: 4
B10: Empada | C10: Kg | D10: 50 | E10: 1 | F10: 4
B11: Quibe | C11: Kg | D11: 50 | E11: 0.5 | F11: 4
B12: Chá | C12: Unidade | D12: 15 | E12: 0.5 | F12: 2
B13: Manteiga | C13: Unidade | D13: 15 | E13: 0.25 | F13: 1
B14: Requeijão | C14: Unidade | D14: 15 | E14: 0.25 | F14: 1
B15: Chocolate Quente | C15: Caixa | D15: 10 | E15: 0.25 | F15: 8.5
B16: Leite | C16: Caixa | D16: 12 | E16: 10 | F16: 5
... B31: Enroladinho | C31: Kg | D31: 10 | E31: 0.25 | F31: 5

Sheet Fornecedor
E1: Cadastro de Fornecedor
B5: Empresa | C5: Telefone | D5: Responsável | E5: E-mail
B6: Mercado Express | C6: (11) 1122-4422 | D6: Maria | E6: maria@mercadoexpress.com.br
B7: Frigorífico Z | C7: (11) 1001-2022 | D7: Carlos | E7: carlos@frigoríficoz.com.br
B8: Distribuídora KS | C8: (11) 1300-4033 | D8: Eduardo | E8: eduardo@distribuídoraks.com.br
B9: Salgados Gran | C9: (11) 1400-3022 | D9: Claudia | E9: claudia@salgadosgran.com.br

Sheet Entradas
F1: Controle de Entradas
B5: Mês | C5: Data | D5: Produto | E5: Fornecedor | F5: Quantidade Comprada | G5: Custo Unitário | H5: Valor da Compra
B6: =MONTH(TB_Entradas[[#This Row],[Data]]) -> 1 | C6: 44566 | D6: Café | E6: Mercado Express | F6: 100 | G6: {=_xlfn.XLOOKUP(TB_Entradas[[#This Row],[Produto]],TB_Produtos[[#All],[Produto]],TB_Produtos[[#All],[Custo Unitário]],"Produto não Encontrado",0,1)} -> 2 | H6: =IFERROR(TB_Entradas[[#This Row],[Quantidade Comprada]]*TB_Entradas[[#This Row],[Custo Unitário]],"Erro ao calcular") -> 200
B7: =MONTH(TB_Entradas[[#This Row],[Data]]) -> 1 | C7: 44566 | D7: Coxinha | E7: Salgados Gran | F7: 100 | G7: {=_xlfn.XLOOKUP(TB_Entradas[[#This Row],[Produto]],TB_Produtos[[#All],[Produto]],TB_Produtos[[#All],[Custo Unitário]],"Produto não Encontrado",0,1)} -> 0.5 | H7: =IFERROR(TB_Entradas[[#This Row],[Quantidade Comprada]]*TB_Entradas[[#This Row],[Custo Unitário]],"Erro ao calcular") -> 50
B8: =MONTH(TB_Entradas[[#This Row],[Data]]) -> 1 | C8: 44576 | D8: Chocolate Quente | E8: Mercado Express | F8: 90 | G8: {=_xlfn.XLOOKUP(TB_Entradas[[#This Row],[Produto]],TB_Produtos[[#All],[Produto]],TB_Produtos[[#All],[Custo Unitário]],"Produto não Encontrado",0,1)} -> 0.25 | H8: =IFERROR(TB_Entradas[[#This Row],[Quantidade Comprada]]*TB_Entradas[[#This Row],[Custo Unitário]],"Erro ao calcular") -> 22.5
B9: =MONTH(TB_Entradas[[#This Row],[Data]]) -> 1 | C9: 44578 | D9: Pão de Queijo | E9: Salgados Gran | F9: 100 | G9: {=_xlfn.XLOOKUP(TB_Entradas[[#This Row],[Produto]],TB_Produtos[[#All],[Produto]],TB_Produtos[[#All],[Custo Unitário]],"Produto não Encontrado",0,1)} -> 0.25 | H9: =IFERROR(TB_Entradas[[#This Row],[Quantidade Comprada]]*TB_Entradas[[#This Row],[Custo Unitário]],"Erro ao calcular") -> 25
B10: =MONTH(TB_Entradas[[#This Row],[Data]]) -> 2 | C10: 44593 | D10: Pão de Queijo | E10: Salgados Gran | F10: 85 | G10: {=_xlfn.XLOOKUP(TB_Entradas[[#This Row],[Produto]],TB_Produtos[[#All],[Produto]],TB_Produtos[[#All],[Custo Unitário]],"Produto não Encontrado",0,1)} -> 0.25 | H10: =IFERROR(TB_Entradas[[#This Row],[Quantidade Comprada]]*TB_Entradas[[#This Row],[Custo Unitário]],"Erro ao calcular") -> 21.25
B11: =MONTH(TB_Entradas[[#This Row],[Data]]) -> 2 | C11: 44594 | D11: Chocolate Quente | E11: Mercado Express | F11: 80 | G11: {=_xlfn.XLOOKUP(TB_Entradas[[#This Row],[Produto]],TB_Produtos[[#All],[Produto]],TB_Produtos[[#All],[Custo Unitário]],"Produto não Encontrado",0,1)} -> 0.25 | H11: =IFERROR(TB_Entradas[[#This Row],[Quantidade Comprada]]*TB_Entradas[[#This Row],[Custo Unitário]],"Erro ao calcular") -> 20
B12: =MONTH(TB_Entradas[[#This Row],[Data]]) -> 2 | C12: 44598 | D12: Café | E12: Mercado Express | F12: 125 | G12: {=_xlfn.XLOOKUP(TB_Entradas[[#This Row],[Produto]],TB_Produtos[[#All],[Produto]],TB_Produtos[[#All],[Custo Unitário]],"Produto não Encontrado",0,1)} -> 2 | H12: =IFERROR(TB_Entradas[[#This Row],[Quantidade Comprada]]*TB_Entradas[[#This Row],[Custo Unitário]],"Erro ao calcular") -> 250
B13: =MONTH(TB_Entradas[[#This Row],[Data]]) -> 2 | C13: 44602 | D13: Cerveja | E13: Distribuídora KS | F13: 50 | G13: {=_xlfn.XLOOKUP(TB_Entradas[[#This Row],[Produto]],TB_Produtos[[#All],[Produto]],TB_Produtos[[#All],[Custo Unitário]],"Produto não Encontrado",0,1)} -> 0.75 | H13: =IFERROR(TB_Entradas[[#This Row],[Quantidade Comprada]]*TB_Entradas[[#This Row],[Custo Unitário]],"Erro ao calcular") -> 37.5
B14: =MONTH(TB_Entradas[[#This Row],[Data]]) -> 2 | C14: 44612 | D14: Coxinha | E14: Salgados Gran | F14: 100 | G14: {=_xlfn.XLOOKUP(TB_Entradas[[#This Row],[Produto]],TB_Produtos[[#All],[Produto]],TB_Produtos[[#All],[Custo Unitário]],"Produto não Encontrado",0,1)} -> 0.5 | H14: =IFERROR(TB_Entradas[[#This Row],[Quantidade Comprada]]*TB_Entradas[[#This Row],[Custo Unitário]],"Erro ao calcular") -> 50
B15: =MONTH(TB_Entradas[[#This Row],[Data]]) -> 3 | C15: 44625 | D15: Refrigerante | E15: Distribuídora KS | F15: 250 | G15: {=_xlfn.XLOOKUP(TB_Entradas[[#This Row],[Produto]],TB_Produtos[[#All],[Produto]],TB_Produtos[[#All],[Custo Unitário]],"Produto não Encontrado",0,1)} -> 2 | H15: =IFERROR(TB_Entradas[[#This Row],[Quantidade Comprada]]*TB_Entradas[[#This Row],[Custo Unitário]],"Erro ao calcular") -> 500
B16: =MONTH(TB_Entradas[[#This Row],[Data]]) -> 3 | C16: 44630 | D16: Pão de Queijo | E16: Salgados Gran | F16: 50 | G16: {=_xlfn.XLOOKUP(TB_Entradas[[#This Row],[Produto]],TB_Produtos[[#All],[Produto]],TB_Produtos[[#All],[Custo Unitário]],"Produto não Encontrado",0,1)} -> 0.25 | H16: =IFERROR(TB_Entradas[[#This Row],[Quantidade Comprada]]*TB_Entradas[[#This Row],[Custo Unitário]],"Erro ao calcular") -> 12.5
B17: =MONTH(TB_Entradas[[#This Row],[Data]]) -> 3 | C17: 44635 | D17: Café | E17: Mercado Express | F17: 150 | G17: {=_xlfn.XLOOKUP(TB_Entradas[[#This Row],[Produto]],TB_Produtos[[#All],[Produto]],TB_Produtos[[#All],[Custo Unitário]],"Produto não Encontrado",0,1)} -> 2 | H17: =IFERROR(TB_Entradas[[#This Row],[Quantidade Comprada]]*TB_Entradas[[#This Row],[Custo Unitário]],"Erro ao calcular") -> 300
... B59: =MONTH(TB_Entradas[[#This Row],[Data]]) -> 12 | C59: 44910 | D59: Chocolate Quente | E59: Mercado Express | F59: 40 | G59: {=_xlfn.XLOOKUP(TB_Entradas[[#This Row],[Produto]],TB_Produtos[[#All],[Produto]],TB_Produtos[[#All],[Custo Unitário]],"Produto não Encontrado",0,1)} -> 0.25 | H59: =IFERROR(TB_Entradas[[#This Row],[Quantidade Comprada]]*TB_Entradas[[#This Row],[Custo Unitário]],"Erro ao calcular") -> 10

Sheet Saídas
E1: Controle de Saídas
B5: Mês | C5: Data | D5: Produto | E5: Quantidade Vendida | F5: Preço Unitário | G5: Valor de Venda
B6: =MONTH(TB_Saídas[[#This Row],[Data]]) -> 1 | C6: 44566 | D6: Coxinha | E6: 30 | F6: {=_xlfn.XLOOKUP(TB_Saídas[[#This Row],[Produto]],TB_Produtos[[#All],[Produto]],TB_Produtos[[#All],[Preço Unitário]],"Produto não Encontrado",0,1)} -> 6.5 | G6: =IFERROR(TB_Saídas[[#This Row],[Quantidade Vendida]]*TB_Saídas[[#This Row],[Preço Unitário]],"Não foi possível calcular") -> 195
B7: =MONTH(TB_Saídas[[#This Row],[Data]]) -> 1 | C7: 44567 | D7: Café | E7: 80 | F7: {=_xlfn.XLOOKUP(TB_Saídas[[#This Row],[Produto]],TB_Produtos[[#All],[Produto]],TB_Produtos[[#All],[Preço Unitário]],"Produto não Encontrado",0,1)} -> 6 | G7: =IFERROR(TB_Saídas[[#This Row],[Quantidade Vendida]]*TB_Saídas[[#This Row],[Preço Unitário]],"Não foi possível calcular") -> 480
B8: =MONTH(TB_Saídas[[#This Row],[Data]]) -> 1 | C8: 44581 | D8: Pão de Queijo | E8: 50 | F8: {=_xlfn.XLOOKUP(TB_Saídas[[#This Row],[Produto]],TB_Produtos[[#All],[Produto]],TB_Produtos[[#All],[Preço Unitário]],"Produto não Encontrado",0,1)} -> 7.5 | G8: =IFERROR(TB_Saídas[[#This Row],[Quantidade Vendida]]*TB_Saídas[[#This Row],[Preço Unitário]],"Não foi possível calcular") -> 375
B9: =MONTH(TB_Saídas[[#This Row],[Data]]) -> 1 | C9: 44586 | D9: Chocolate Quente | E9: 50 | F9: {=_xlfn.XLOOKUP(TB_Saídas[[#This Row],[Produto]],TB_Produtos[[#All],[Produto]],TB_Produtos[[#All],[Preço Unitário]],"Produto não Encontrado",0,1)} -> 8.5 | G9: =IFERROR(TB_Saídas[[#This Row],[Quantidade Vendida]]*TB_Saídas[[#This Row],[Preço Unitário]],"Não foi possível calcular") -> 425
B10: =MONTH(TB_Saídas[[#This Row],[Data]]) -> 2 | C10: 44597 | D10: Pão de Queijo | E10: 30 | F10: {=_xlfn.XLOOKUP(TB_Saídas[[#This Row],[Produto]],TB_Produtos[[#All],[Produto]],TB_Produtos[[#All],[Preço Unitário]],"Produto não Encontrado",0,1)} -> 7.5 | G10: =IFERROR(TB_Saídas[[#This Row],[Quantidade Vendida]]*TB_Saídas[[#This Row],[Preço Unitário]],"Não foi possível calcular") -> 225
B11: =MONTH(TB_Saídas[[#This Row],[Data]]) -> 2 | C11: 44598 | D11: Café | E11: 110 | F11: {=_xlfn.XLOOKUP(TB_Saídas[[#This Row],[Produto]],TB_Produtos[[#All],[Produto]],TB_Produtos[[#All],[Preço Unitário]],"Produto não Encontrado",0,1)} -> 6 | G11: =IFERROR(TB_Saídas[[#This Row],[Quantidade Vendida]]*TB_Saídas[[#This Row],[Preço Unitário]],"Não foi possível calcular") -> 660
B12: =MONTH(TB_Saídas[[#This Row],[Data]]) -> 2 | C12: 44602 | D12: Chocolate Quente | E12: 75 | F12: {=_xlfn.XLOOKUP(TB_Saídas[[#This Row],[Produto]],TB_Produtos[[#All],[Produto]],TB_Produtos[[#All],[Preço Unitário]],"Produto não Encontrado",0,1)} -> 8.5 | G12: =IFERROR(TB_Saídas[[#This Row],[Quantidade Vendida]]*TB_Saídas[[#This Row],[Preço Unitário]],"Não foi possível calcular") -> 637.5
B13: =MONTH(TB_Saídas[[#This Row],[Data]]) -> 2 | C13: 44620 | D13: Coxinha | E13: 20 | F13: {=_xlfn.XLOOKUP(TB_Saídas[[#This Row],[Produto]],TB_Produtos[[#All],[Produto]],TB_Produtos[[#All],[Preço Unitário]],"Produto não Encontrado",0,1)} -> 6.5 | G13: =IFERROR(TB_Saídas[[#This Row],[Quantidade Vendida]]*TB_Saídas[[#This Row],[Preço Unitário]],"Não foi possível calcular") -> 130
B14: =MONTH(TB_Saídas[[#This Row],[Data]]) -> 3 | C14: 44626 | D14: Refrigerante | E14: 110 | F14: {=_xlfn.XLOOKUP(TB_Saídas[[#This Row],[Produto]],TB_Produtos[[#All],[Produto]],TB_Produtos[[#All],[Preço Unitário]],"Produto não Encontrado",0,1)} -> 8 | G14: =IFERROR(TB_Saídas[[#This Row],[Quantidade Vendida]]*TB_Saídas[[#This Row],[Preço Unitário]],"Não foi possível calcular") -> 880
B15: =MONTH(TB_Saídas[[#This Row],[Data]]) -> 3 | C15: 44631 | D15: Pão de Queijo | E15: 40 | F15: {=_xlfn.XLOOKUP(TB_Saídas[[#This Row],[Produto]],TB_Produtos[[#All],[Produto]],TB_Produtos[[#All],[Preço Unitário]],"Produto não Encontrado",0,1)} -> 7.5 | G15: =IFERROR(TB_Saídas[[#This Row],[Quantidade Vendida]]*TB_Saídas[[#This Row],[Preço Unitário]],"Não foi possível calcular") -> 300
B16: =MONTH(TB_Saídas[[#This Row],[Data]]) -> 3 | C16: 44646 | D16: Chocolate Quente | E16: 50 | F16: {=_xlfn.XLOOKUP(TB_Saídas[[#This Row],[Produto]],TB_Produtos[[#All],[Produto]],TB_Produtos[[#All],[Preço Unitário]],"Produto não Encontrado",0,1)} -> 8.5 | G16: =IFERROR(TB_Saídas[[#This Row],[Quantidade Vendida]]*TB_Saídas[[#This Row],[Preço Unitário]],"Não foi possível calcular") -> 425
B17: =MONTH(TB_Saídas[[#This Row],[Data]]) -> 3 | C17: 44649 | D17: Coxinha | E17: 15 | F17: {=_xlfn.XLOOKUP(TB_Saídas[[#This Row],[Produto]],TB_Produtos[[#All],[Produto]],TB_Produtos[[#All],[Preço Unitário]],"Produto não Encontrado",0,1)} -> 6.5 | G17: =IFERROR(TB_Saídas[[#This Row],[Quantidade Vendida]]*TB_Saídas[[#This Row],[Preço Unitário]],"Não foi possível calcular") -> 97.5
... B62: =MONTH(TB_Saídas[[#This Row],[Data]]) -> 12 | C62: 44917 | D62: Chocolate Quente | E62: 23 | F62: {=_xlfn.XLOOKUP(TB_Saídas[[#This Row],[Produto]],TB_Produtos[[#All],[Produto]],TB_Produtos[[#All],[Preço Unitário]],"Produto não Encontrado",0,1)} -> 8.5 | G62: =IFERROR(TB_Saídas[[#This Row],[Quantidade Vendida]]*TB_Saídas[[#This Row],[Preço Unitário]],"Não foi possível calcular") -> 195.5

Sheet Consulta
G1: Consulta
D5: Data | F5: Produto
D6: <10/05/2022 | F6: ="=Café" -> =Café
D8: Quantidade Vendida | F8: =DSUM(TB_Saídas[#All],Consulta!D8,Consulta!D5:F6) -> 365
D10: Quantidade em Estoque | F10: =DSUM(TB_Entradas[#All],"Quantidade Comprada",Consulta!D5:F6)-F8 -> 160
D12: Valor da Compra | F12: =DSUM(TB_Entradas[#All],Consulta!D12,Consulta!D5:F6) -> 1050
D14: Valor de Venda | F14: =DSUM(TB_Saídas[#All],Consulta!D14,Consulta!D5:F6) -> 2190

Sheet Controle de Estoque
F1: Controle de Estoque
B5: Produto | C5: Entradas | D5: Saídas | E5: Saldo em Estoque | F5: Estoque Mínimo | G5: Status do Estoque | H5: Valor de Venda | I5: Custo Total | J5: Lucro
B6: Refrigerante | C6: =IFERROR(SUMIF(TB_Entradas[Produto],TB_ControleEstoque[[#This Row],[Produto]],TB_Entradas[Quantidade Comprada]),0) -> 350 | D6: =IFERROR(SUMIF(TB_Saídas[Produto],TB_ControleEstoque[[#This Row],[Produto]],TB_Saídas[Quantidade Vendida]),0) -> 210 | E6: =TB_ControleEstoque[[#This Row],[Entradas]]-TB_ControleEstoque[[#This Row],[Saídas ]] -> 140 | F6: =_xlfn.XLOOKUP(TB_ControleEstoque[[#This Row],[Produto]],TB_Produtos[Produto],TB_Produtos[Estoque Mínimo],"Erro",0,1) -> 10 | G6: {=_xlfn.IFS(TB_ControleEstoque[[#This Row],[Saldo em Estoque]]>TB_ControleEstoque[[#This Row],[Estoque Mínimo]],"Estoque OK",TB_ControleEstoque[[#This Row],[Saldo em Estoque]]=0,"Estoque Zerado",1,"Repor Estoque")} -> Estoque OK | H6: =SUMIFS(TB_Saídas[Valor de Venda],TB_Saídas[Produto],TB_ControleEstoque[[#This Row],[Produto]]) -> 1680 | I6: =SUMIFS(TB_Entradas[Valor da Compra],TB_Entradas[Produto],TB_ControleEstoque[[#This Row],[Produto]]) -> 700 | J6: =TB_ControleEstoque[[#This Row],[Valor de Venda]]-TB_ControleEstoque[[#This Row],[Custo Total]] -> 980
B7: Café | C7: =IFERROR(SUMIF(TB_Entradas[Produto],TB_ControleEstoque[[#This Row],[Produto]],TB_Entradas[Quantidade Comprada]),0) -> 1635 | D7: =IFERROR(SUMIF(TB_Saídas[Produto],TB_ControleEstoque[[#This Row],[Produto]],TB_Saídas[Quantidade Vendida]),0) -> 945 | E7: =TB_ControleEstoque[[#This Row],[Entradas]]-TB_ControleEstoque[[#This Row],[Saídas ]] -> 690 | F7: =_xlfn.XLOOKUP(TB_ControleEstoque[[#This Row],[Produto]],TB_Produtos[Produto],TB_Produtos[Estoque Mínimo],"Erro",0,1) -> 50 | G7: {=_xlfn.IFS(TB_ControleEstoque[[#This Row],[Saldo em Estoque]]>TB_ControleEstoque[[#This Row],[Estoque Mínimo]],"Estoque OK",TB_ControleEstoque[[#This Row],[Saldo em Estoque]]=0,"Estoque Zerado",1,"Repor Estoque")} -> Estoque OK | H7: =SUMIFS(TB_Saídas[Valor de Venda],TB_Saídas[Produto],TB_ControleEstoque[[#This Row],[Produto]]) -> 5670 | I7: =SUMIFS(TB_Entradas[Valor da Compra],TB_Entradas[Produto],TB_ControleEstoque[[#This Row],[Produto]]) -> 3270 | J7: =TB_ControleEstoque[[#This Row],[Valor de Venda]]-TB_ControleEstoque[[#This Row],[Custo Total]] -> 2400 | N7: Produto Mais Rentável
B8: Suco de Laranja | C8: =IFERROR(SUMIF(TB_Entradas[Produto],TB_ControleEstoque[[#This Row],[Produto]],TB_Entradas[Quantidade Comprada]),0) -> 100 | D8: =IFERROR(SUMIF(TB_Saídas[Produto],TB_ControleEstoque[[#This Row],[Produto]],TB_Saídas[Quantidade Vendida]),0) -> 100 | E8: =TB_ControleEstoque[[#This Row],[Entradas]]-TB_ControleEstoque[[#This Row],[Saídas ]] -> 0 | F8: =_xlfn.XLOOKUP(TB_ControleEstoque[[#This Row],[Produto]],TB_Produtos[Produto],TB_Produtos[Estoque Mínimo],"Erro",0,1) -> 5 | G8: {=_xlfn.IFS(TB_ControleEstoque[[#This Row],[Saldo em Estoque]]>TB_ControleEstoque[[#This Row],[Estoque Mínimo]],"Estoque OK",TB_ControleEstoque[[#This Row],[Saldo em Estoque]]=0,"Estoque Zerado",1,"Repor Estoque")} -> Estoque Zerado | H8: =SUMIFS(TB_Saídas[Valor de Venda],TB_Saídas[Produto],TB_ControleEstoque[[#This Row],[Produto]]) -> 1000 | I8: =SUMIFS(TB_Entradas[Valor da Compra],TB_Entradas[Produto],TB_ControleEstoque[[#This Row],[Produto]]) -> 75 | J8: =TB_ControleEstoque[[#This Row],[Valor de Venda]]-TB_ControleEstoque[[#This Row],[Custo Total]] -> 925 | N8: Lucro | P8: Produto
B9: Cerveja | C9: =IFERROR(SUMIF(TB_Entradas[Produto],TB_ControleEstoque[[#This Row],[Produto]],TB_Entradas[Quantidade Comprada]),0) -> 50 | D9: =IFERROR(SUMIF(TB_Saídas[Produto],TB_ControleEstoque[[#This Row],[Produto]],TB_Saídas[Quantidade Vendida]),0) -> 25 | E9: =TB_ControleEstoque[[#This Row],[Entradas]]-TB_ControleEstoque[[#This Row],[Saídas ]] -> 25 | F9: =_xlfn.XLOOKUP(TB_ControleEstoque[[#This Row],[Produto]],TB_Produtos[Produto],TB_Produtos[Estoque Mínimo],"Erro",0,1) -> 5 | G9: {=_xlfn.IFS(TB_ControleEstoque[[#This Row],[Saldo em Estoque]]>TB_ControleEstoque[[#This Row],[Estoque Mínimo]],"Estoque OK",TB_ControleEstoque[[#This Row],[Saldo em Estoque]]=0,"Estoque Zerado",1,"Repor Estoque")} -> Estoque OK | H9: =SUMIFS(TB_Saídas[Valor de Venda],TB_Saídas[Produto],TB_ControleEstoque[[#This Row],[Produto]]) -> 200 | I9: =SUMIFS(TB_Entradas[Valor da Compra],TB_Entradas[Produto],TB_ControleEstoque[[#This Row],[Produto]]) -> 37.5 | J9: =TB_ControleEstoque[[#This Row],[Valor de Venda]]-TB_ControleEstoque[[#This Row],[Custo Total]] -> 162.5 | N9: =LARGE(TB_ControleEstoque[Lucro],1) -> 4062.5 | P9: =DGET(TB_ControleEstoque[#All],1,N8:N9) -> Chocolate Quente
B10: Chocolate Quente | C10: =IFERROR(SUMIF(TB_Entradas[Produto],TB_ControleEstoque[[#This Row],[Produto]],TB_Entradas[Quantidade Comprada]),0) -> 750 | D10: =IFERROR(SUMIF(TB_Saídas[Produto],TB_ControleEstoque[[#This Row],[Produto]],TB_Saídas[Quantidade Vendida]),0) -> 500 | E10: =TB_ControleEstoque[[#This Row],[Entradas]]-TB_ControleEstoque[[#This Row],[Saídas ]] -> 250 | F10: =_xlfn.XLOOKUP(TB_ControleEstoque[[#This Row],[Produto]],TB_Produtos[Produto],TB_Produtos[Estoque Mínimo],"Erro",0,1) -> 10 | G10: {=_xlfn.IFS(TB_ControleEstoque[[#This Row],[Saldo em Estoque]]>TB_ControleEstoque[[#This Row],[Estoque Mínimo]],"Estoque OK",TB_ControleEstoque[[#This Row],[Saldo em Estoque]]=0,"Estoque Zerado",1,"Repor Estoque")} -> Estoque OK | H10: =SUMIFS(TB_Saídas[Valor de Venda],TB_Saídas[Produto],TB_ControleEstoque[[#This Row],[Produto]]) -> 4250 | I10: =SUMIFS(TB_Entradas[Valor da Compra],TB_Entradas[Produto],TB_ControleEstoque[[#This Row],[Produto]]) -> 187.5 | J10: =TB_ControleEstoque[[#This Row],[Valor de Venda]]-TB_ControleEstoque[[#This Row],[Custo Total]] -> 4062.5
B11: Pão de Queijo | C11: =IFERROR(SUMIF(TB_Entradas[Produto],TB_ControleEstoque[[#This Row],[Produto]],TB_Entradas[Quantidade Comprada]),0) -> 620 | D11: =IFERROR(SUMIF(TB_Saídas[Produto],TB_ControleEstoque[[#This Row],[Produto]],TB_Saídas[Quantidade Vendida]),0) -> 400 | E11: =TB_ControleEstoque[[#This Row],[Entradas]]-TB_ControleEstoque[[#This Row],[Saídas ]] -> 220 | F11: =_xlfn.XLOOKUP(TB_ControleEstoque[[#This Row],[Produto]],TB_Produtos[Produto],TB_Produtos[Estoque Mínimo],"Erro",0,1) -> 10 | G11: {=_xlfn.IFS(TB_ControleEstoque[[#This Row],[Saldo em Estoque]]>TB_ControleEstoque[[#This Row],[Estoque Mínimo]],"Estoque OK",TB_ControleEstoque[[#This Row],[Saldo em Estoque]]=0,"Estoque Zerado",1,"Repor Estoque")} -> Estoque OK | H11: =SUMIFS(TB_Saídas[Valor de Venda],TB_Saídas[Produto],TB_ControleEstoque[[#This Row],[Produto]]) -> 3000 | I11: =SUMIFS(TB_Entradas[Valor da Compra],TB_Entradas[Produto],TB_ControleEstoque[[#This Row],[Produto]]) -> 155 | J11: =TB_ControleEstoque[[#This Row],[Valor de Venda]]-TB_ControleEstoque[[#This Row],[Custo Total]] -> 2845
B12: Coxinha | C12: =IFERROR(SUMIF(TB_Entradas[Produto],TB_ControleEstoque[[#This Row],[Produto]],TB_Entradas[Quantidade Comprada]),0) -> 550 | D12: =IFERROR(SUMIF(TB_Saídas[Produto],TB_ControleEstoque[[#This Row],[Produto]],TB_Saídas[Quantidade Vendida]),0) -> 245 | E12: =TB_ControleEstoque[[#This Row],[Entradas]]-TB_ControleEstoque[[#This Row],[Saídas ]] -> 305 | F12: =_xlfn.XLOOKUP(TB_ControleEstoque[[#This Row],[Produto]],TB_Produtos[Produto],TB_Produtos[Estoque Mínimo],"Erro",0,1) -> 50 | G12: {=_xlfn.IFS(TB_ControleEstoque[[#This Row],[Saldo em Estoque]]>TB_ControleEstoque[[#This Row],[Estoque Mínimo]],"Estoque OK",TB_ControleEstoque[[#This Row],[Saldo em Estoque]]=0,"Estoque Zerado",1,"Repor Estoque")} -> Estoque OK | H12: =SUMIFS(TB_Saídas[Valor de Venda],TB_Saídas[Produto],TB_ControleEstoque[[#This Row],[Produto]]) -> 1592.5 | I12: =SUMIFS(TB_Entradas[Valor da Compra],TB_Entradas[Produto],TB_ControleEstoque[[#This Row],[Produto]]) -> 275 | J12: =TB_ControleEstoque[[#This Row],[Valor de Venda]]-TB_ControleEstoque[[#This Row],[Custo Total]] -> 1317.5
B13: Frango | C13: =IFERROR(SUMIF(TB_Entradas[Produto],TB_ControleEstoque[[#This Row],[Produto]],TB_Entradas[Quantidade Comprada]),0) -> 50 | D13: =IFERROR(SUMIF(TB_Saídas[Produto],TB_ControleEstoque[[#This Row],[Produto]],TB_Saídas[Quantidade Vendida]),0) -> 30 | E13: =TB_ControleEstoque[[#This Row],[Entradas]]-TB_ControleEstoque[[#This Row],[Saídas ]] -> 20 | F13: =_xlfn.XLOOKUP(TB_ControleEstoque[[#This Row],[Produto]],TB_Produtos[Produto],TB_Produtos[Estoque Mínimo],"Erro",0,1) -> 2 | G13: {=_xlfn.IFS(TB_ControleEstoque[[#This Row],[Saldo em Estoque]]>TB_ControleEstoque[[#This Row],[Estoque Mínimo]],"Estoque OK",TB_ControleEstoque[[#This Row],[Saldo em Estoque]]=0,"Estoque Zerado",1,"Repor Estoque")} -> Estoque OK | H13: =SUMIFS(TB_Saídas[Valor de Venda],TB_Saídas[Produto],TB_ControleEstoque[[#This Row],[Produto]]) -> 450 | I13: =SUMIFS(TB_Entradas[Valor da Compra],TB_Entradas[Produto],TB_ControleEstoque[[#This Row],[Produto]]) -> 225 | J13: =TB_ControleEstoque[[#This Row],[Valor de Venda]]-TB_ControleEstoque[[#This Row],[Custo Total]] -> 225
B14: Mini Pizza | C14: =IFERROR(SUMIF(TB_Entradas[Produto],TB_ControleEstoque[[#This Row],[Produto]],TB_Entradas[Quantidade Comprada]),0) -> 100 | D14: =IFERROR(SUMIF(TB_Saídas[Produto],TB_ControleEstoque[[#This Row],[Produto]],TB_Saídas[Quantidade Vendida]),0) -> 90 | E14: =TB_ControleEstoque[[#This Row],[Entradas]]-TB_ControleEstoque[[#This Row],[Saídas ]] -> 10 | F14: =_xlfn.XLOOKUP(TB_ControleEstoque[[#This Row],[Produto]],TB_Produtos[Produto],TB_Produtos[Estoque Mínimo],"Erro",0,1) -> 10 | G14: {=_xlfn.IFS(TB_ControleEstoque[[#This Row],[Saldo em Estoque]]>TB_ControleEstoque[[#This Row],[Estoque Mínimo]],"Estoque OK",TB_ControleEstoque[[#This Row],[Saldo em Estoque]]=0,"Estoque Zerado",1,"Repor Estoque")} -> Repor Estoque | H14: =SUMIFS(TB_Saídas[Valor de Venda],TB_Saídas[Produto],TB_ControleEstoque[[#This Row],[Produto]]) -> 450 | I14: =SUMIFS(TB_Entradas[Valor da Compra],TB_Entradas[Produto],TB_ControleEstoque[[#This Row],[Produto]]) -> 100 | J14: =TB_ControleEstoque[[#This Row],[Valor de Venda]]-TB_ControleEstoque[[#This Row],[Custo Total]] -> 350
B15: Hamburguer | C15: =IFERROR(SUMIF(TB_Entradas[Produto],TB_ControleEstoque[[#This Row],[Produto]],TB_Entradas[Quantidade Comprada]),0) -> 60 | D15: =IFERROR(SUMIF(TB_Saídas[Produto],TB_ControleEstoque[[#This Row],[Produto]],TB_Saídas[Quantidade Vendida]),0) -> 50 | E15: =TB_ControleEstoque[[#This Row],[Entradas]]-TB_ControleEstoque[[#This Row],[Saídas ]] -> 10 | F15: =_xlfn.XLOOKUP(TB_ControleEstoque[[#This Row],[Produto]],TB_Produtos[Produto],TB_Produtos[Estoque Mínimo],"Erro",0,1) -> 2 | G15: {=_xlfn.IFS(TB_ControleEstoque[[#This Row],[Saldo em Estoque]]>TB_ControleEstoque[[#This Row],[Estoque Mínimo]],"Estoque OK",TB_ControleEstoque[[#This Row],[Saldo em Estoque]]=0,"Estoque Zerado",1,"Repor Estoque")} -> Estoque OK | H15: =SUMIFS(TB_Saídas[Valor de Venda],TB_Saídas[Produto],TB_ControleEstoque[[#This Row],[Produto]]) -> 750 | I15: =SUMIFS(TB_Entradas[Valor da Compra],TB_Entradas[Produto],TB_ControleEstoque[[#This Row],[Produto]]) -> 480 | J15: =TB_ControleEstoque[[#This Row],[Valor de Venda]]-TB_ControleEstoque[[#This Row],[Custo Total]] -> 270

Sheet Quadro de Resumo
AD1: Quadro de Resumo
C5: Dados 2022 | AB5: Consulta por Produto
AM7: Produto
D8: Produtos Vendidos: | N8: =COUNTA(_xlfn.UNIQUE(TB_Saídas[Produto])) -> 10 | AC8: Dados: | AM8: Café
D11: Qtd em Estoque: | N11: =SUM(TB_ControleEstoque[Saldo em Estoque]) -> 1670 | AC11: Qtd em Estoque: | AM11: =DSUM(TB_ControleEstoque[#All],TB_ControleEstoque[[#Headers],[Saldo em Estoque]],CriteriosConsultaProduto) -> 690
D14: Faturamento: | N14: =SUM(TB_Saídas[Valor de Venda]) -> 19042.5 | AC14: Faturamento: | AM14: =DSUM(TB_Saídas[#All],TB_Saídas[[#Headers],[Valor de Venda]],CriteriosConsultaProduto) -> 5670
D17: Despesas: | N17: =SUM(TB_Entradas[Valor da Compra]) -> 5530 | AC17: Despesas: | AM17: =DSUM(TB_Entradas[#All],TB_Entradas[[#Headers],[Valor da Compra]],CriteriosConsultaProduto) -> 3270
D20: Lucro: | N20: =N14-N17 -> 13512.5 | AC20: Lucro: | AM20: =AM14-AM17 -> 2400
D23: % Lucro: | N23: =N20/N17 -> 2.4434901 | AC23: % Lucro: | AM23: =AM20/AM17 -> 0.73394495

Sheet Top 5 Mais vendidos
A1: {=TB_Produtos[Produto]} -> Café | B1: =SUMIF(TB_Saídas[Produto],A1,TB_Saídas[Quantidade Vendida]) -> 945 | E1: {=TB_Produtos[Produto]} -> Café | F1: =SUMIF(TB_Saídas[Produto],A1,TB_Saídas[Valor de Venda]) -> 5670
A2: Pão | B2: =SUMIF(TB_Saídas[Produto],A2,TB_Saídas[Quantidade Vendida]) -> 0 | E2: Pão | F2: =SUMIF(TB_Saídas[Produto],A2,TB_Saídas[Valor de Venda]) -> 0
A3: Coxinha | B3: =SUMIF(TB_Saídas[Produto],A3,TB_Saídas[Quantidade Vendida]) -> 245 | E3: Coxinha | F3: =SUMIF(TB_Saídas[Produto],A3,TB_Saídas[Valor de Venda]) -> 1592.5
A4: Esfiha | B4: =SUMIF(TB_Saídas[Produto],A4,TB_Saídas[Quantidade Vendida]) -> 0 | E4: Esfiha | F4: =SUMIF(TB_Saídas[Produto],A4,TB_Saídas[Valor de Venda]) -> 0
A5: Risoles | B5: =SUMIF(TB_Saídas[Produto],A5,TB_Saídas[Quantidade Vendida]) -> 0 | E5: Risoles | F5: =SUMIF(TB_Saídas[Produto],A5,TB_Saídas[Valor de Venda]) -> 0
A6: Empada | B6: =SUMIF(TB_Saídas[Produto],A6,TB_Saídas[Quantidade Vendida]) -> 0 | E6: Empada | F6: =SUMIF(TB_Saídas[Produto],A6,TB_Saídas[Valor de Venda]) -> 0
A7: Quibe | B7: =SUMIF(TB_Saídas[Produto],A7,TB_Saídas[Quantidade Vendida]) -> 0 | E7: Quibe | F7: =SUMIF(TB_Saídas[Produto],A7,TB_Saídas[Valor de Venda]) -> 0
A8: Chá | B8: =SUMIF(TB_Saídas[Produto],A8,TB_Saídas[Quantidade Vendida]) -> 0 | E8: Chá | F8: =SUMIF(TB_Saídas[Produto],A8,TB_Saídas[Valor de Venda]) -> 0
A9: Manteiga | B9: =SUMIF(TB_Saídas[Produto],A9,TB_Saídas[Quantidade Vendida]) -> 0 | E9: Manteiga | F9: =SUMIF(TB_Saídas[Produto],A9,TB_Saídas[Valor de Venda]) -> 0
A10: Requeijão | B10: =SUMIF(TB_Saídas[Produto],A10,TB_Saídas[Quantidade Vendida]) -> 0 | E10: Requeijão | F10: =SUMIF(TB_Saídas[Produto],A10,TB_Saídas[Valor de Venda]) -> 0
A11: Chocolate Quente | B11: =SUMIF(TB_Saídas[Produto],A11,TB_Saídas[Quantidade Vendida]) -> 500 | E11: Chocolate Quente | F11: =SUMIF(TB_Saídas[Produto],A11,TB_Saídas[Valor de Venda]) -> 4250
A12: Leite | B12: =SUMIF(TB_Saídas[Produto],A12,TB_Saídas[Quantidade Vendida]) -> 0 | E12: Leite | F12: =SUMIF(TB_Saídas[Produto],A12,TB_Saídas[Valor de Venda]) -> 0
A13: Açúcar | B13: =SUMIF(TB_Saídas[Produto],A13,TB_Saídas[Quantidade Vendida]) -> 0 | E13: Açúcar | F13: =SUMIF(TB_Saídas[Produto],A13,TB_Saídas[Valor de Venda]) -> 0
... A27: Enroladinho | B27: =SUMIF(TB_Saídas[Produto],A27,TB_Saídas[Quantidade Vendida]) -> 0 | E27: Enroladinho | F27: =SUMIF(TB_Saídas[Produto],A27,TB_Saídas[Valor de Venda]) -> 0

Sheet Base de cálculo
A1: Ranking | B1: Produto | C1: Qtd vendida | D1: Qtd comprada | F1: Faturamento VS Despesas | K1: Produto | L1: Entradas e Saídas (Qtd) | P1: Anual
A2: 1 | B2: =_xlfn.XLOOKUP(C2,'Top 5 Mais vendidos'!B:B,'Top 5 Mais vendidos'!A:A) -> Café | C2: =LARGE('Top 5 Mais vendidos'!B:B,'Base de cálculo'!A2) -> 945 | D2: =SUMIF(TB_Entradas[Produto],B2,TB_Entradas[Quantidade Comprada]) -> 1635 | F2: N. Mês | G2: Mês | H2: Faturamento | I2: Despesas | K2: =Dashboard!AN30 -> Café | L2: Mês | M2: Entradas | N2: Saídas | P2: Entradas | Q2: =SUM(M3:M14) -> 1635
A3: 2 | B3: =_xlfn.XLOOKUP(C3,'Top 5 Mais vendidos'!B:B,'Top 5 Mais vendidos'!A:A) -> Chocolate Quente | C3: =LARGE('Top 5 Mais vendidos'!B:B,'Base de cálculo'!A3) -> 500 | D3: =SUMIF(TB_Entradas[Produto],B3,TB_Entradas[Quantidade Comprada]) -> 750 | F3: 1 | G3: =DATE(,F3,1) -> 1 | H3: =SUMIF(TB_Saídas[Mês],F3,TB_Saídas[Valor de Venda]) -> 1475 | I3: =SUMIF(TB_Entradas[Mês],F3,TB_Entradas[Valor da Compra]) -> 297.5 | L3: jan | M3: =SUMIFS(TB_Entradas[Quantidade Comprada],TB_Entradas[Produto],$K$2,TB_Entradas[Mês],$F3) -> 100 | N3: =SUMIFS(TB_Saídas[Quantidade Vendida],TB_Saídas[Produto],$K$2,TB_Saídas[Mês],$F3) -> 80 | P3: Saídas | Q3: =SUM(N3:N14) -> 945
A4: 3 | B4: =_xlfn.XLOOKUP(C4,'Top 5 Mais vendidos'!B:B,'Top 5 Mais vendidos'!A:A) -> Pão de Queijo | C4: =LARGE('Top 5 Mais vendidos'!B:B,'Base de cálculo'!A4) -> 400 | D4: =SUMIF(TB_Entradas[Produto],B4,TB_Entradas[Quantidade Comprada]) -> 620 | F4: 2 | G4: =DATE(,F4,1) -> 32 | H4: =SUMIF(TB_Saídas[Mês],F4,TB_Saídas[Valor de Venda]) -> 1652.5 | I4: =SUMIF(TB_Entradas[Mês],F4,TB_Entradas[Valor da Compra]) -> 378.75 | L4: fev | M4: =SUMIFS(TB_Entradas[Quantidade Comprada],TB_Entradas[Produto],$K$2,TB_Entradas[Mês],$F4) -> 125 | N4: =SUMIFS(TB_Saídas[Quantidade Vendida],TB_Saídas[Produto],$K$2,TB_Saídas[Mês],$F4) -> 110
A5: 4 | B5: =_xlfn.XLOOKUP(C5,'Top 5 Mais vendidos'!B:B,'Top 5 Mais vendidos'!A:A) -> Coxinha | C5: =LARGE('Top 5 Mais vendidos'!B:B,'Base de cálculo'!A5) -> 245 | D5: =SUMIF(TB_Entradas[Produto],B5,TB_Entradas[Quantidade Comprada]) -> 550 | F5: 3 | G5: =DATE(,F5,1) -> 61 | H5: =SUMIF(TB_Saídas[Mês],F5,TB_Saídas[Valor de Venda]) -> 2302.5 | I5: =SUMIF(TB_Entradas[Mês],F5,TB_Entradas[Valor da Compra]) -> 922.5 | L5: mar | M5: =SUMIFS(TB_Entradas[Quantidade Comprada],TB_Entradas[Produto],$K$2,TB_Entradas[Mês],$F5) -> 150 | N5: =SUMIFS(TB_Saídas[Quantidade Vendida],TB_Saídas[Produto],$K$2,TB_Saídas[Mês],$F5) -> 100
A6: 5 | B6: =_xlfn.XLOOKUP(C6,'Top 5 Mais vendidos'!B:B,'Top 5 Mais vendidos'!A:A) -> Refrigerante | C6: =LARGE('Top 5 Mais vendidos'!B:B,'Base de cálculo'!A6) -> 210 | D6: =SUMIF(TB_Entradas[Produto],B6,TB_Entradas[Quantidade Comprada]) -> 350 | F6: 4 | G6: =DATE(,F6,1) -> 92 | H6: =SUMIF(TB_Saídas[Mês],F6,TB_Saídas[Valor de Venda]) -> 1507.5 | I6: =SUMIF(TB_Entradas[Mês],F6,TB_Entradas[Valor da Compra]) -> 362.5 | L6: abr | M6: =SUMIFS(TB_Entradas[Quantidade Comprada],TB_Entradas[Produto],$K$2,TB_Entradas[Mês],$F6) -> 150 | N6: =SUMIFS(TB_Saídas[Quantidade Vendida],TB_Saídas[Produto],$K$2,TB_Saídas[Mês],$F6) -> 75
F7: 5 | G7: =DATE(,F7,1) -> 122 | H7: =SUMIF(TB_Saídas[Mês],F7,TB_Saídas[Valor de Venda]) -> 1372 | I7: =SUMIF(TB_Entradas[Mês],F7,TB_Entradas[Valor da Compra]) -> 723.75 | L7: mai | M7: =SUMIFS(TB_Entradas[Quantidade Comprada],TB_Entradas[Produto],$K$2,TB_Entradas[Mês],$F7) -> 100 | N7: =SUMIFS(TB_Saídas[Quantidade Vendida],TB_Saídas[Produto],$K$2,TB_Saídas[Mês],$F7) -> 75
A8: Raking | B8: Produto | C8: Faturamento | F8: 6 | G8: =DATE(,F8,1) -> 153 | H8: =SUMIF(TB_Saídas[Mês],F8,TB_Saídas[Valor de Venda]) -> 1145 | I8: =SUMIF(TB_Entradas[Mês],F8,TB_Entradas[Valor da Compra]) -> 376.25 | L8: jun | M8: =SUMIFS(TB_Entradas[Quantidade Comprada],TB_Entradas[Produto],$K$2,TB_Entradas[Mês],$F8) -> 150 | N8: =SUMIFS(TB_Saídas[Quantidade Vendida],TB_Saídas[Produto],$K$2,TB_Saídas[Mês],$F8) -> 100
A9: 1 | B9: =_xlfn.XLOOKUP(C9,'Top 5 Mais vendidos'!F:F,'Top 5 Mais vendidos'!E:E) -> Café | C9: =LARGE('Top 5 Mais vendidos'!F:F,'Base de cálculo'!A9) -> 5670 | F9: 7 | G9: =DATE(,F9,1) -> 183 | H9: =SUMIF(TB_Saídas[Mês],F9,TB_Saídas[Valor de Venda]) -> 2217.5 | I9: =SUMIF(TB_Entradas[Mês],F9,TB_Entradas[Valor da Compra]) -> 355 | L9: jul | M9: =SUMIFS(TB_Entradas[Quantidade Comprada],TB_Entradas[Produto],$K$2,TB_Entradas[Mês],$F9) -> 150 | N9: =SUMIFS(TB_Saídas[Quantidade Vendida],TB_Saídas[Produto],$K$2,TB_Saídas[Mês],$F9) -> 90
A10: 2 | B10: =_xlfn.XLOOKUP(C10,'Top 5 Mais vendidos'!F:F,'Top 5 Mais vendidos'!E:E) -> Chocolate Quente | C10: =LARGE('Top 5 Mais vendidos'!F:F,'Base de cálculo'!A10) -> 4250 | F10: 8 | G10: =DATE(,F10,1) -> 214 | H10: =SUMIF(TB_Saídas[Mês],F10,TB_Saídas[Valor de Venda]) -> 1621.5 | I10: =SUMIF(TB_Entradas[Mês],F10,TB_Entradas[Valor da Compra]) -> 431.25 | L10: ago | M10: =SUMIFS(TB_Entradas[Quantidade Comprada],TB_Entradas[Produto],$K$2,TB_Entradas[Mês],$F10) -> 150 | N10: =SUMIFS(TB_Saídas[Quantidade Vendida],TB_Saídas[Produto],$K$2,TB_Saídas[Mês],$F10) -> 100
A11: 3 | B11: =_xlfn.XLOOKUP(C11,'Top 5 Mais vendidos'!F:F,'Top 5 Mais vendidos'!E:E) -> Pão de Queijo | C11: =LARGE('Top 5 Mais vendidos'!F:F,'Base de cálculo'!A11) -> 3000 | F11: 9 | G11: =DATE(,F11,1) -> 245 | H11: =SUMIF(TB_Saídas[Mês],F11,TB_Saídas[Valor de Venda]) -> 2234 | I11: =SUMIF(TB_Entradas[Mês],F11,TB_Entradas[Valor da Compra]) -> 806 | L11: set | M11: =SUMIFS(TB_Entradas[Quantidade Comprada],TB_Entradas[Produto],$K$2,TB_Entradas[Mês],$F11) -> 180 | N11: =SUMIFS(TB_Saídas[Quantidade Vendida],TB_Saídas[Produto],$K$2,TB_Saídas[Mês],$F11) -> 35
A12: 4 | B12: =_xlfn.XLOOKUP(C12,'Top 5 Mais vendidos'!F:F,'Top 5 Mais vendidos'!E:E) -> Refrigerante | C12: =LARGE('Top 5 Mais vendidos'!F:F,'Base de cálculo'!A12) -> 1680 | F12: 10 | G12: =DATE(,F12,1) -> 275 | H12: =SUMIF(TB_Saídas[Mês],F12,TB_Saídas[Valor de Venda]) -> 1508 | I12: =SUMIF(TB_Entradas[Mês],F12,TB_Entradas[Valor da Compra]) -> 247.75 | L12: out | M12: =SUMIFS(TB_Entradas[Quantidade Comprada],TB_Entradas[Produto],$K$2,TB_Entradas[Mês],$F12) -> 100 | N12: =SUMIFS(TB_Saídas[Quantidade Vendida],TB_Saídas[Produto],$K$2,TB_Saídas[Mês],$F12) -> 30
A13: 5 | B13: =_xlfn.XLOOKUP(C13,'Top 5 Mais vendidos'!F:F,'Top 5 Mais vendidos'!E:E) -> Coxinha | C13: =LARGE('Top 5 Mais vendidos'!F:F,'Base de cálculo'!A13) -> 1592.5 | F13: 11 | G13: =DATE(,F13,1) -> 306 | H13: =SUMIF(TB_Saídas[Mês],F13,TB_Saídas[Valor de Venda]) -> 811.5 | I13: =SUMIF(TB_Entradas[Mês],F13,TB_Entradas[Valor da Compra]) -> 218.75 | L13: nov | M13: =SUMIFS(TB_Entradas[Quantidade Comprada],TB_Entradas[Produto],$K$2,TB_Entradas[Mês],$F13) -> 80 | N13: =SUMIFS(TB_Saídas[Quantidade Vendida],TB_Saídas[Produto],$K$2,TB_Saídas[Mês],$F13) -> 50
F14: 12 | G14: =DATE(,F14,1) -> 336 | H14: =SUMIF(TB_Saídas[Mês],F14,TB_Saídas[Valor de Venda]) -> 1195.5 | I14: =SUMIF(TB_Entradas[Mês],F14,TB_Entradas[Valor da Compra]) -> 410 | L14: dez | M14: =SUMIFS(TB_Entradas[Quantidade Comprada],TB_Entradas[Produto],$K$2,TB_Entradas[Mês],$F14) -> 200 | N14: =SUMIFS(TB_Saídas[Quantidade Vendida],TB_Saídas[Produto],$K$2,TB_Saídas[Mês],$F14) -> 100

Sheet Dashboard
B1: DASHBOARD
AF2: FATURAMENTO | AX2: DESPESAS | BP2: LUCRO
AF4: =SUM(TB_Saídas[Valor de Venda]) -> 19042.5 | AX4: =SUM(TB_Entradas[Valor da Compra]) -> 5530 | BP4: =(AF4-AX4)/AX4 -> 2.4434901
C8: TOP 5 PRODUTOS MAIS VENDIDOS
AB9: FATURAMENTO X DESPESA
AB28: ENTRADA X SAÍDA MENSAL | BP28: ENTRADA X SAÍDA ANUAL
C29: RANKING FATURAMENTO
AN30: Café
C31: 1º | G31: ='Base de cálculo'!B9 -> Café | Q31: ='Base de cálculo'!C9 -> 5670
C34: 2º | G34: ='Base de cálculo'!B10 -> Chocolate Quente | Q34: ='Base de cálculo'!C10 -> 4250
C37: 3º | G37: ='Base de cálculo'!B11 -> Pão de Queijo | Q37: ='Base de cálculo'!C11 -> 3000
C40: 4º | G40: ='Base de cálculo'!B12 -> Refrigerante | Q40: ='Base de cálculo'!C12 -> 1680
C43: 5º | G43: ='Base de cálculo'!B13 -> Coxinha | Q43: ='Base de cálculo'!C13 -> 1592.5
